{
    "speechBackground": "dialogue/dialogueyside",
    "speechBackgroundPos": ["", ""],
    "speechBackgroundAnim": [],
    "speechTextFont": "FredokaOne-Regular.ttf",
    "speechContinueThingSprite": "dialogue/continueThing",
    "speechContinueThingOffsets": [-70, -90],
    "speechBackgroundSize": [1, 1],
    "dialogues": 
    [
        {
            "dialogue": "Yo!",
            "textSpeed": 0.04,
            "speechTextOffsets": [40, 40],
            "speechTextWidth": 1170,
            "currentCharacter":
            {
                "name": "dialogue/BF_Dialogue",
                "position": [800, 160],
                "anims": 
                [
                    ["normla", [0, 0]],
                    ["normla", [0, 0]]
                ],
                "sounds": ["bftext"],
                "addBehind": true
            },
            "background": 
            {
                "name": "dialogue/background",
                "position": [0, 0],
                "anims": []
            }
        },
        {
            "dialogue": "Uh...",
            "textSpeed": 0.04,
            "speechTextOffsets": [40, 40],
            "speechTextWidth": 1170,
            "currentCharacter":
            {
                "name": "dialogue/DAD_Dialogue",
                "position": [70, 60],
                "anims": 
                [
                    ["normal", [0, 0]],
                    ["normal", [0, 0]]
                ],
                "sounds": ["dadtext"],
                "addBehind": true
            },
            "background": 
            {
                "name": "dialogue/background",
                "position": [0, 0],
                "anims": []
            }
        },
        {
            "dialogue": "Who the hell are you?",
            "textSpeed": 0.04,
            "speechTextOffsets": [40, 40],
            "speechTextWidth": 1170,
            "currentCharacter":
            {
                "name": "dialogue/DAD_Dialogue",
                "position": [70, 60],
                "anims": 
                [
                    ["normal", [0, 0]],
                    ["normal", [0, 0]]
                ],
                "sounds": ["dadtext"],
                "addBehind": true
            },
            "background": 
            {
                "name": "dialogue/background",
                "position": [0, 0],
                "anims": []
            }
        },
        {
            "dialogue": "Ermm hey! It's me! Ummm, I'm your daugther's boyfriend...",
            "textSpeed": 0.04,
            "speechTextOffsets": [40, 40],
            "speechTextWidth": 1170,
            "currentCharacter":
            {
                "name": "dialogue/BF_Dialogue",
                "position": [800, 160],
                "anims": 
                [
                    ["rarp", [0, 0]],
                    ["rarp", [0, 0]]
                ],
                "sounds": ["bftext"],
                "addBehind": true
            },
            "background": 
            {
                "name": "dialogue/background",
                "position": [0, 0],
                "anims": []
            }
        },
        {
            "dialogue": "I thought you already knew about me...",
            "textSpeed": 0.04,
            "speechTextOffsets": [40, 40],
            "speechTextWidth": 1170,
            "currentCharacter":
            {
                "name": "dialogue/BF_Dialogue",
                "position": [800, 160],
                "anims": 
                [
                    ["papichulo", [0, 0]],
                    ["papichulo", [0, 0]]
                ],
                "sounds": ["bftext"],
                "addBehind": true
            },
            "background": 
            {
                "name": "dialogue/background",
                "position": [0, 0],
                "anims": []
            }
        },
        {
            "dialogue": "Don't worry dad! He's super cute and nice. He even likes gym like you",
            "textSpeed": 0.04,
            "speechTextOffsets": [40, 40],
            "speechTextWidth": 1170,
            "currentCharacter":
            {
                "name": "dialogue/GF_Dialogue",
                "position": [500, 190],
                "anims": 
                [
                    ["normla", [0, 0]],
                    ["normla", [0, 0]]
                ],
                "sounds": ["gftext"],
                "addBehind": true
            },
            "background": 
            {
                "name": "dialogue/background",
                "position": [0, 0],
                "anims": []
            }
        },
        {
            "dialogue": "HAHA! No one likes gym like me!",
            "textSpeed": 0.04,
            "speechTextOffsets": [40, 40],
            "speechTextWidth": 1170,
            "currentCharacter":
            {
                "name": "dialogue/DAD_Dialogue",
                "position": [70, 60],
                "anims": 
                [
                    ["serious", [0, 0]],
                    ["serious", [0, 0]]
                ],
                "sounds": ["dadtext"],
                "addBehind": true
            },
            "background": 
            {
                "name": "dialogue/background",
                "position": [0, 0],
                "anims": []
            }
        },
        {
            "dialogue": "Listen lil buddy, if you want to date my daughter, you have to prove yourself!",
            "textSpeed": 0.04,
            "speechTextOffsets": [40, 40],
            "speechTextWidth": 1170,
            "currentCharacter":
            {
                "name": "dialogue/DAD_Dialogue",
                "position": [70, 60],
                "anims": 
                [
                    ["serious", [0, 0]],
                    ["serious", [0, 0]]
                ],
                "sounds": ["dadtext"],
                "addBehind": true
            },
            "background": 
            {
                "name": "dialogue/background",
                "position": [0, 0],
                "anims": []
            }
        },
        {
            "dialogue": "Oh.",
            "textSpeed": 0.04,
            "speechTextOffsets": [40, 40],
            "speechTextWidth": 1170,
            "currentCharacter":
            {
                "name": "dialogue/BF_Dialogue",
                "position": [800, 160],
                "anims": 
                [
                    ["normla", [0, 0]],
                    ["normla", [0, 0]]
                ],
                "sounds": ["bftext"],
                "addBehind": true
            },
            "background": 
            {
                "name": "dialogue/background",
                "position": [0, 0],
                "anims": []
            }
        },
        {
            "dialogue": "Sure! >:)",
            "textSpeed": 0.04,
            "speechTextOffsets": [40, 40],
            "speechTextWidth": 1170,
            "currentCharacter":
            {
                "name": "dialogue/BF_Dialogue",
                "position": [800, 160],
                "anims": 
                [
                    ["serious", [0, 0]],
                    ["serious", [0, 0]]
                ],
                "sounds": ["bftext"],
                "addBehind": true
            },
            "background": 
            {
                "name": "dialogue/background",
                "position": [0, 0],
                "anims": []
            }
        }
    ]
}